apitorch/__init__.py
apitorch/api_client.py
apitorch/classifier.py
apitorch/errors.py
apitorch/ping.py
apitorch/routes.py
apitorch/statics.py
apitorch/training_image.py
apitorch/training_set.py
apitorch/utils.py
apitorch-0.0.19.dist-info/METADATA
apitorch-0.0.19.dist-info/WHEEL
apitorch-0.0.19.dist-info/top_level.txt
apitorch-0.0.19.dist-info/RECORD
