Metadata-Version: 2.1
Name: apitorch
Version: 0.0.19
Summary: API Torch Python client
Home-page: https://github.com/apitorch/apitorch.py
License: MIT
Platform: UNKNOWN
Classifier: Intended Audience :: Developers
Classifier: Operating System :: OS Independent
Classifier: Programming Language :: Python :: 3
Requires-Dist: requests (<3.0,>=2.20.0)
